bcedd/__init__.py
bcedd/__main__.py
bcedd/country_code.py
bcedd/crypto.py
bcedd/event_data.py
bcedd/game_version.py
bcedd/json_file.py
bcedd/request.py
bcedd/files/version.txt
bcedd-1.2.1.dist-info/LICENSE
bcedd-1.2.1.dist-info/METADATA
bcedd-1.2.1.dist-info/WHEEL
bcedd-1.2.1.dist-info/top_level.txt
bcedd-1.2.1.dist-info/RECORD
