Metadata-Version: 2.1
Name: bcedd
Version: 1.2.1
Home-page: https://github.com/fieryhenry/bcedd
Author: fieryhenry
Classifier: Programming Language :: Python :: 3
Classifier: License :: OSI Approved :: MIT License
Classifier: Operating System :: OS Independent
Requires-Python: >=3.9
License-File: LICENSE
Requires-Dist: requests
